{
  "source": "altinkaynak",
  "guncellenme_local": "24.03.2026 22:16:05",
  "guncellenme_utc": "2026-03-24T22:16:05.298953+00:00",
  "counts": {
    "altinlar": 11,
    "dovizler": 13,
    "toplam": 24
  },
  "altinlar": [
    {
      "isim": "Has Toptan",
      "alis": 6787.0,
      "satis": 6905.06
    },
    {
      "isim": "Külçe Toptan",
      "alis": 6753.06,
      "satis": 6870.53
    },
    {
      "isim": "Ata Cumhuriyet",
      "alis": 45023.72,
      "satis": 49900.0
    },
    {
      "isim": "Çeyrek Altın",
      "alis": 11005.33,
      "satis": 12300.0
    },
    {
      "isim": "Yarım Altın",
      "alis": 21838.55,
      "satis": 24600.0
    },
    {
      "isim": "Teklik Altın",
      "alis": 43637.88,
      "satis": 49200.0
    },
    {
      "isim": "Gremse Altın",
      "alis": 108865.95,
      "satis": 124750.0
    },
    {
      "isim": "Ata Beşli",
      "alis": 222740.18,
      "satis": 249500.0
    },
    {
      "isim": "Resat Altın",
      "alis": 44763.44,
      "satis": 49900.0
    },
    {
      "isim": "Hamit Altın",
      "alis": 44763.44,
      "satis": 49900.0
    },
    {
      "isim": "Gram Altın",
      "alis": 6753.06,
      "satis": 6950.0
    }
  ],
  "dovizler": [
    {
      "isim": "Amerikan Doları",
      "alis": 44.845,
      "satis": 45.204
    },
    {
      "isim": "Avrupa Para Birimi",
      "alis": 51.771,
      "satis": 52.413
    },
    {
      "isim": "İngiliz Sterlini",
      "alis": 59.818,
      "satis": 60.799
    },
    {
      "isim": "Japon Yeni",
      "alis": 0.2787,
      "satis": 0.2854
    },
    {
      "isim": "S. Arabistan Riyali",
      "alis": 11.882,
      "satis": 12.085
    },
    {
      "isim": "Avustralya Doları",
      "alis": 30.72,
      "satis": 31.566
    },
    {
      "isim": "Kanada Doları",
      "alis": 32.315,
      "satis": 32.944
    },
    {
      "isim": "Rus Rublesi",
      "alis": 0.5002,
      "satis": 0.5995
    },
    {
      "isim": "Azerbaycan Manatı",
      "alis": 24.921,
      "satis": 26.892
    },
    {
      "isim": "Çin Yuanı",
      "alis": 5.928,
      "satis": 7.101
    },
    {
      "isim": "Romanya Leyi",
      "alis": 8.794,
      "satis": 10.454
    },
    {
      "isim": "B.A.E. Dirhemi",
      "alis": 11.18,
      "satis": 12.911
    },
    {
      "isim": "Kuveyt Dinarı",
      "alis": 133.29,
      "satis": 150.572
    }
  ]
}