{
  "source": "altinkaynak",
  "guncellenme_local": "24.04.2026 17:32:14",
  "guncellenme_utc": "2026-04-24T17:32:14.252445+00:00",
  "counts": {
    "altinlar": 11,
    "dovizler": 13,
    "toplam": 24
  },
  "altinlar": [
    {
      "isim": "Has Toptan",
      "alis": 6799.02,
      "satis": 6848.64
    },
    {
      "isim": "Külçe Toptan",
      "alis": 6765.03,
      "satis": 6814.39
    },
    {
      "isim": "Ata Cumhuriyet",
      "alis": 45103.5,
      "satis": 49500.0
    },
    {
      "isim": "Çeyrek Altın",
      "alis": 11011.74,
      "satis": 11900.0
    },
    {
      "isim": "Yarım Altın",
      "alis": 21877.25,
      "satis": 23800.0
    },
    {
      "isim": "Teklik Altın",
      "alis": 43715.21,
      "satis": 47600.0
    },
    {
      "isim": "Gremse Altın",
      "alis": 109058.86,
      "satis": 119000.0
    },
    {
      "isim": "Ata Beşli",
      "alis": 223134.87,
      "satis": 247500.0
    },
    {
      "isim": "Resat Altın",
      "alis": 44582.02,
      "satis": 49500.0
    },
    {
      "isim": "Hamit Altın",
      "alis": 44582.02,
      "satis": 49500.0
    },
    {
      "isim": "Gram Altın",
      "alis": 6765.03,
      "satis": 6960.0
    }
  ],
  "dovizler": [
    {
      "isim": "Amerikan Doları",
      "alis": 44.825,
      "satis": 45.018
    },
    {
      "isim": "Avrupa Para Birimi",
      "alis": 52.417,
      "satis": 52.743
    },
    {
      "isim": "İngiliz Sterlini",
      "alis": 60.247,
      "satis": 61.072
    },
    {
      "isim": "Japon Yeni",
      "alis": 0.2773,
      "satis": 0.283
    },
    {
      "isim": "S. Arabistan Riyali",
      "alis": 11.861,
      "satis": 12.02
    },
    {
      "isim": "Avustralya Doları",
      "alis": 31.409,
      "satis": 32.155
    },
    {
      "isim": "Kanada Doları",
      "alis": 32.505,
      "satis": 33.017
    },
    {
      "isim": "Rus Rublesi",
      "alis": 0.535,
      "satis": 0.6388
    },
    {
      "isim": "Azerbaycan Manatı",
      "alis": 24.909,
      "satis": 26.781
    },
    {
      "isim": "Çin Yuanı",
      "alis": 5.978,
      "satis": 7.134
    },
    {
      "isim": "Romanya Leyi",
      "alis": 8.885,
      "satis": 10.523
    },
    {
      "isim": "B.A.E. Dirhemi",
      "alis": 11.175,
      "satis": 12.858
    },
    {
      "isim": "Kuveyt Dinarı",
      "alis": 126.842,
      "satis": 149.424
    }
  ]
}